alu/alu.v
module alu(
    input  [3:0] a,
    input  [3:0] b,
    input  [3:0] op,
    output reg [3:0] result,
    output reg zero
);
    always @(*) begin
        case(op)
            4'b0000: result = a + b;
            4'b0001: result = a - b;
            4'b0010: result = a & b;
            4'b0011: result = a | b;
            4'b0100: result = a ^ b;
            4'b0101: result = ~a;
            4'b0110: result = a << 1;
            4'b0111: result = a >> 1;
            4'b1000: result = a << 2;
            4'b1001: result = a >> 2;
            4'b1010: result = ~(a & b);
            4'b1011: result = ~(a | b);
            4'b1100: result = ~(a ^ b);
            4'b1101: result = (a == b) ? 4'b0001 : 4'b0000;
            4'b1110: result = (a < b)  ? 4'b0001 : 4'b0000;
            4'b1111: result = (a > b)  ? 4'b0001 : 4'b0000;
            default: result = 4'b0000;
        endcase
        zero = (result == 4'b0000) ? 1 : 0;
    end
endmodule

alu/alu_tb.v
module alu_tb;
    reg  [3:0] a, b, op;
    wire [3:0] result;
    wire zero;

    alu uut (.a(a), .b(b), .op(op), .result(result), .zero(zero));

    initial begin
        $dumpfile("alu.vcd");
        $dumpvars(0, alu_tb);

        a=4'd5; b=4'd3; op=4'b0000; #10;
        $display("ADD:  %0d + %0d = %0d", a, b, result);

        a=4'd5; b=4'd3; op=4'b0001; #10;
        $display("SUB:  %0d - %0d = %0d", a, b, result);

        a=4'd5; b=4'd3; op=4'b0010; #10;
        $display("AND:  %0d & %0d = %0d", a, b, result);

        a=4'd5; b=4'd3; op=4'b0011; #10;
        $display("OR:   %0d | %0d = %0d", a, b, result);

        a=4'd5; b=4'd3; op=4'b0100; #10;
        $display("XOR:  %0d ^ %0d = %0d", a, b, result);

        a=4'd5; b=4'd3; op=4'b0101; #10;
        $display("NOT:  ~%0d = %0d", a, result);

        a=4'd5; b=4'd3; op=4'b0110; #10;
        $display("SHL1: %0d << 1 = %0d", a, result);

        a=4'd5; b=4'd3; op=4'b0111; #10;
        $display("SHR1: %0d >> 1 = %0d", a, result);

        a=4'd5; b=4'd3; op=4'b1000; #10;
        $display("SHL2: %0d << 2 = %0d", a, result);

        a=4'd5; b=4'd3; op=4'b1001; #10;
        $display("SHR2: %0d >> 2 = %0d", a, result);

        a=4'd5; b=4'd3; op=4'b1010; #10;
        $display("NAND: ~(%0d & %0d) = %0d", a, b, result);

        a=4'd5; b=4'd3; op=4'b1011; #10;
        $display("NOR:  ~(%0d | %0d) = %0d", a, b, result);

        a=4'd5; b=4'd3; op=4'b1100; #10;
        $display("XNOR: ~(%0d ^ %0d) = %0d", a, b, result);

        a=4'd5; b=4'd5; op=4'b1101; #10;
        $display("EQ:   %0d == %0d = %0d", a, b, result);

        a=4'd3; b=4'd5; op=4'b1110; #10;
        $display("LT:   %0d < %0d = %0d", a, b, result);

        a=4'd5; b=4'd3; op=4'b1111; #10;
        $display("GT:   %0d > %0d = %0d", a, b, result);

        $finish;
    end
endmodule

alu/alu.vcd
$date
	Tue May 26 08:13:03 2026
$end
$version
	Icarus Verilog
$end
$timescale
	1s
$end
$scope module alu_tb $end
$var wire 1 ! zero $end
$var wire 4 " result [3:0] $end
$var reg 4 # a [3:0] $end
$var reg 4 $ b [3:0] $end
$var reg 4 % op [3:0] $end
$scope module uut $end
$var wire 4 & a [3:0] $end
$var wire 4 ' b [3:0] $end
$var wire 4 ( op [3:0] $end
$var reg 4 ) result [3:0] $end
$var reg 1 ! zero $end
$upscope $end
$upscope $end
$enddefinitions $end
$comment Show the parameter values. $end
$dumpall
$end
#0
$dumpvars
b1000 )
b0 (
b11 '
b101 &
b0 %
b11 $
b101 #
b1000 "
0!
$end
#10
b10 "
b10 )
b1 %
b1 (
#20
b1 "
b1 )
b10 %
b10 (
#30
b111 "
b111 )
b11 %
b11 (
#40
b110 "
b110 )
b100 %
b100 (
#50
b1010 "
b1010 )
b101 %
b101 (
#60
b110 %
b110 (
#70
b10 "
b10 )
b111 %
b111 (
#80
b100 "
b100 )
b1000 %
b1000 (
#90
b1 "
b1 )
b1001 %
b1001 (
#100
b1110 "
b1110 )
b1010 %
b1010 (
#110
b1000 "
b1000 )
b1011 %
b1011 (
#120
b1001 "
b1001 )
b1100 %
b1100 (
#130
b1 "
b1 )
b1101 %
b1101 (
b101 $
b101 '
#140
b1110 %
b1110 (
b11 #
b11 &
#150
b1111 %
b1111 (
b11 $
b11 '
b101 #
b101 &
